supermgr/__init__.py
supermgr/_version.py
supermgr/action.py
supermgr/cli.py
supermgr/config.py
supermgr/procs.py
supermgr/server.py
supermgr/worker.py
supermgr-0.16.dist-info/METADATA
supermgr-0.16.dist-info/RECORD
supermgr-0.16.dist-info/WHEEL
supermgr-0.16.dist-info/entry_points.txt
supermgr-0.16.dist-info/top_level.txt
