Metadata-Version: 2.1
Name: supermgr
Version: 0.16
Summary: Easier Management of individual supervisord processes
Home-page: https://github.com/ksgh/supermgr
Author: Kyle Shenk
Author-email: k.shenk@gmail.com
License: MIT
Platform: UNKNOWN
Requires-Dist: colorama
Requires-Dist: argparse
Requires-Dist: tailer
